LICENCE
README
setup.py
cdebug/__init__.py
cdebug/__main__.py
cdebug/cdebug.py
cdebug.egg-info/PKG-INFO
cdebug.egg-info/SOURCES.txt
cdebug.egg-info/dependency_links.txt
cdebug.egg-info/top_level.txt