Metadata-Version: 2.4
Name: cdebug
Version: 0.0.2
Summary: debug
Home-page: https://github.com/wayne931121
Author: wayne931121
Author-email: 
License: CC-BY-NC 4.0
Classifier: Programming Language :: Python :: 3
Classifier: Operating System :: OS Independent
Requires-Python: >=3.0
License-File: LICENCE
Dynamic: author
Dynamic: classifier
Dynamic: description
Dynamic: description-content-type
Dynamic: home-page
Dynamic: license
Dynamic: license-file
Dynamic: requires-python
Dynamic: summary
